simplebets/bet.py
simplebets/head_to_head.py
simplebets/individual_metrics.py
simplebets/league.py
simplebets/market.py
simplebets/participant.py
simplebets/same_game_multi.py
simplebets-1.0.1.dist-info/METADATA
simplebets-1.0.1.dist-info/WHEEL
simplebets-1.0.1.dist-info/top_level.txt
simplebets-1.0.1.dist-info/zip-safe
simplebets-1.0.1.dist-info/RECORD
